tap_workato/__init__.py
tap_workato/client.py
tap_workato/streams.py
tap_workato/tap.py
tap_workato/tests/__init__.py
tap_workato/tests/test_core.py
tap_workato-0.1.1.dist-info/entry_points.txt
tap_workato-0.1.1.dist-info/LICENSE
tap_workato-0.1.1.dist-info/WHEEL
tap_workato-0.1.1.dist-info/METADATA
tap_workato-0.1.1.dist-info/RECORD
