Metadata-Version: 2.1
Name: tap-workato
Version: 0.1.1
Summary: `tap-workato` is a Singer tap for Workato, built with the Meltano SDK for Singer Taps.
Home-page: https://github.com/Widen/tap-workato
License: Apache 2.0
Keywords: ELT,Workato,Singer,tap
Author: Josh Lloyd
Requires-Python: >=3.7.1,<3.11
Classifier: License :: Other/Proprietary License
Classifier: Programming Language :: Python :: 3
Classifier: Programming Language :: Python :: 3.10
Classifier: Programming Language :: Python :: 3.8
Classifier: Programming Language :: Python :: 3.9
Requires-Dist: requests (>=2.25.1,<3.0.0)
Requires-Dist: singer-sdk (>=0.13.1,<0.14.0)
Project-URL: Repository, https://github.com/Widen/tap-workato
